systems/__init__.py
systems/_systems/BaseSys.py
systems/_systems/HenonMap.py
systems/_systems/HindmarshRose.py
systems/_systems/LogisticMap.py
systems/_systems/Lorenz.py
systems/_systems/Rossler.py
systems/_systems/Ueda.py
systems/_systems/VanDerPol.py
systems/_systems/__init__.py
tools/__init__.py
tools/_tools/DensityEstimation.py
tools/_tools/__init__.py
tools/_tools/corr_utils.py
tools/_tools/math_utils.py
pykeos-0.0.2.dist-info/METADATA
pykeos-0.0.2.dist-info/WHEEL
pykeos-0.0.2.dist-info/top_level.txt
pykeos-0.0.2.dist-info/RECORD
