Metadata-Version: 2.1
Name: pykeos
Version: 0.0.2
Summary: UNKNOWN
Home-page: UNKNOWN
Author: Johan Medrano
Author-email: 
License: UNKNOWN
Platform: Linux
Classifier: Development Status :: 3 - Alpha
Classifier: Natural Language :: English
Classifier: Programming Language :: Python
Classifier: Programming Language :: Python :: 3.6
Classifier: Programming Language :: Python :: 3.7
Requires-Python: >=3.4
Requires-Dist: nolds
Requires-Dist: plotly
Requires-Dist: plotly-orca
Requires-Dist: plotly-express
Requires-Dist: pyunicorn
